[
  {
    "type": "class",
    "id": "FormHistoryStartup",
    "line": 11,
    "methods": [
      {
        "type": "method",
        "id": "observe",
        "line": 19,
        "params": [
          {
            "type": "params",
            "id": "_subject",
            "line": 19
          },
          {
            "type": "params",
            "id": "topic",
            "line": 19
          },
          {
            "type": "params",
            "id": "_data",
            "line": 19
          }
        ],
        "kind": "method"
      },
      {
        "type": "method",
        "id": "init",
        "line": 31,
        "params": [],
        "kind": "method"
      },
      {
        "type": "method",
        "id": "receiveMessage",
        "line": 48,
        "params": [
          {
            "type": "params",
            "id": "message",
            "line": 48
          }
        ],
        "kind": "method"
      }
    ]
  }
]