[
  {
    "type": "variable-declaration",
    "id": "UnitTestObjs",
    "line": 9,
    "typeEstimation": {
      "type": "object-estimation",
      "keys": []
    }
  },
  {
    "type": "class",
    "id": "FfiConverterString",
    "superClass": "FfiConverter",
    "line": 245,
    "methods": [
      {
        "type": "method",
        "id": "checkType",
        "line": 246,
        "params": [
          {
            "type": "params",
            "id": "value",
            "line": 246
          }
        ],
        "kind": "method"
      },
      {
        "type": "method",
        "id": "lift",
        "line": 253,
        "params": [
          {
            "type": "params",
            "id": "buf",
            "line": 253
          }
        ],
        "kind": "method"
      },
      {
        "type": "method",
        "id": "lower",
        "line": 258,
        "params": [
          {
            "type": "params",
            "id": "value",
            "line": 258
          }
        ],
        "kind": "method"
      },
      {
        "type": "method",
        "id": "write",
        "line": 263,
        "params": [
          {
            "type": "params",
            "id": "dataStream",
            "line": 263
          },
          {
            "type": "params",
            "id": "value",
            "line": 263
          }
        ],
        "kind": "method"
      },
      {
        "type": "method",
        "id": "read",
        "line": 267,
        "params": [
          {
            "type": "params",
            "id": "dataStream",
            "line": 267
          }
        ],
        "kind": "method"
      },
      {
        "type": "method",
        "id": "computeSize",
        "line": 271,
        "params": [
          {
            "type": "params",
            "id": "value",
            "line": 271
          }
        ],
        "kind": "method"
      }
    ]
  },
  {
    "type": "class",
    "id": "TodoList",
    "line": 277,
    "methods": [
      {
        "type": "method",
        "id": "constructor",
        "line": 280,
        "params": [
          {
            "type": "params",
            "id": "opts",
            "line": 280
          }
        ],
        "comments": [
          {
            "description": "Use `init` to instantiate this class.",
            "tags": [],
            "source": [
              {
                "number": 0,
                "source": "/**",
                "tokens": {
                  "start": "",
                  "delimiter": "/**",
                  "postDelimiter": "",
                  "tag": "",
                  "postTag": "",
                  "name": "",
                  "postName": "",
                  "type": "",
                  "postType": "",
                  "description": "",
                  "end": "",
                  "lineEnd": ""
                }
              },
              {
                "number": 1,
                "source": " Use `init` to instantiate this class.",
                "tokens": {
                  "start": " ",
                  "delimiter": "",
                  "postDelimiter": "",
                  "tag": "",
                  "postTag": "",
                  "name": "",
                  "postName": "",
                  "type": "",
                  "postType": "",
                  "description": "Use `init` to instantiate this class.",
                  "end": "",
                  "lineEnd": ""
                }
              },
              {
                "number": 2,
                "source": "*/",
                "tokens": {
                  "start": "",
                  "delimiter": "",
                  "postDelimiter": "",
                  "tag": "",
                  "postTag": "",
                  "name": "",
                  "postName": "",
                  "type": "",
                  "postType": "",
                  "description": "",
                  "end": "*/",
                  "lineEnd": ""
                }
              }
            ],
            "problems": []
          },
          {
            "description": "DO NOT USE THIS CONSTRUCTOR DIRECTLY",
            "tags": [],
            "source": [
              {
                "number": 0,
                "source": "/**",
                "tokens": {
                  "start": "",
                  "delimiter": "/**",
                  "postDelimiter": "",
                  "tag": "",
                  "postTag": "",
                  "name": "",
                  "postName": "",
                  "type": "",
                  "postType": "",
                  "description": "",
                  "end": "",
                  "lineEnd": ""
                }
              },
              {
                "number": 1,
                "source": " DO NOT USE THIS CONSTRUCTOR DIRECTLY",
                "tokens": {
                  "start": " ",
                  "delimiter": "",
                  "postDelimiter": "",
                  "tag": "",
                  "postTag": "",
                  "name": "",
                  "postName": "",
                  "type": "",
                  "postType": "",
                  "description": "DO NOT USE THIS CONSTRUCTOR DIRECTLY",
                  "end": "",
                  "lineEnd": ""
                }
              },
              {
                "number": 2,
                "source": "*/",
                "tokens": {
                  "start": "",
                  "delimiter": "",
                  "postDelimiter": "",
                  "tag": "",
                  "postTag": "",
                  "name": "",
                  "postName": "",
                  "type": "",
                  "postType": "",
                  "description": "",
                  "end": "*/",
                  "lineEnd": ""
                }
              }
            ],
            "problems": []
          }
        ],
        "kind": "constructor"
      },
      {
        "type": "method",
        "id": "init",
        "line": 296,
        "params": [],
        "comments": [
          {
            "description": "An async constructor for TodoList.",
            "tags": [
              {
                "tag": "returns",
                "name": ":",
                "type": "Promise<TodoList>",
                "optional": false,
                "description": "A promise that resolves to a newly constructed TodoList",
                "problems": [],
                "source": [
                  {
                    "number": 4,
                    "source": "     * @returns {Promise<TodoList>}: A promise that resolves",
                    "tokens": {
                      "start": "     ",
                      "delimiter": "*",
                      "postDelimiter": " ",
                      "tag": "@returns",
                      "postTag": " ",
                      "name": ":",
                      "postName": " ",
                      "type": "{Promise<TodoList>}",
                      "postType": "",
                      "description": "A promise that resolves",
                      "end": "",
                      "lineEnd": ""
                    }
                  },
                  {
                    "number": 5,
                    "source": "     *      to a newly constructed TodoList",
                    "tokens": {
                      "start": "     ",
                      "delimiter": "*",
                      "postDelimiter": "      ",
                      "tag": "",
                      "postTag": "",
                      "name": "",
                      "postName": "",
                      "type": "",
                      "postType": "",
                      "description": "to a newly constructed TodoList",
                      "end": "",
                      "lineEnd": ""
                    }
                  },
                  {
                    "number": 6,
                    "source": "     ",
                    "tokens": {
                      "start": "     ",
                      "delimiter": "",
                      "postDelimiter": "",
                      "tag": "",
                      "postTag": "",
                      "name": "",
                      "postName": "",
                      "type": "",
                      "postType": "",
                      "description": "",
                      "end": "",
                      "lineEnd": ""
                    }
                  },
                  {
                    "number": 7,
                    "source": "*/",
                    "tokens": {
                      "start": "",
                      "delimiter": "",
                      "postDelimiter": "",
                      "tag": "",
                      "postTag": "",
                      "name": "",
                      "postName": "",
                      "type": "",
                      "postType": "",
                      "description": "",
                      "end": "*/",
                      "lineEnd": ""
                    }
                  }
                ]
              }
            ],
            "source": [
              {
                "number": 0,
                "source": "/**",
                "tokens": {
                  "start": "",
                  "delimiter": "/**",
                  "postDelimiter": "",
                  "tag": "",
                  "postTag": "",
                  "name": "",
                  "postName": "",
                  "type": "",
                  "postType": "",
                  "description": "",
                  "end": "",
                  "lineEnd": ""
                }
              },
              {
                "number": 1,
                "source": "*",
                "tokens": {
                  "start": "",
                  "delimiter": "*",
                  "postDelimiter": "",
                  "tag": "",
                  "postTag": "",
                  "name": "",
                  "postName": "",
                  "type": "",
                  "postType": "",
                  "description": "",
                  "end": "",
                  "lineEnd": ""
                }
              },
              {
                "number": 2,
                "source": "     * An async constructor for TodoList.",
                "tokens": {
                  "start": "     ",
                  "delimiter": "*",
                  "postDelimiter": " ",
                  "tag": "",
                  "postTag": "",
                  "name": "",
                  "postName": "",
                  "type": "",
                  "postType": "",
                  "description": "An async constructor for TodoList.",
                  "end": "",
                  "lineEnd": ""
                }
              },
              {
                "number": 3,
                "source": "     * ",
                "tokens": {
                  "start": "     ",
                  "delimiter": "*",
                  "postDelimiter": " ",
                  "tag": "",
                  "postTag": "",
                  "name": "",
                  "postName": "",
                  "type": "",
                  "postType": "",
                  "description": "",
                  "end": "",
                  "lineEnd": ""
                }
              },
              {
                "number": 4,
                "source": "     * @returns {Promise<TodoList>}: A promise that resolves",
                "tokens": {
                  "start": "     ",
                  "delimiter": "*",
                  "postDelimiter": " ",
                  "tag": "@returns",
                  "postTag": " ",
                  "name": ":",
                  "postName": " ",
                  "type": "{Promise<TodoList>}",
                  "postType": "",
                  "description": "A promise that resolves",
                  "end": "",
                  "lineEnd": ""
                }
              },
              {
                "number": 5,
                "source": "     *      to a newly constructed TodoList",
                "tokens": {
                  "start": "     ",
                  "delimiter": "*",
                  "postDelimiter": "      ",
                  "tag": "",
                  "postTag": "",
                  "name": "",
                  "postName": "",
                  "type": "",
                  "postType": "",
                  "description": "to a newly constructed TodoList",
                  "end": "",
                  "lineEnd": ""
                }
              },
              {
                "number": 6,
                "source": "     ",
                "tokens": {
                  "start": "     ",
                  "delimiter": "",
                  "postDelimiter": "",
                  "tag": "",
                  "postTag": "",
                  "name": "",
                  "postName": "",
                  "type": "",
                  "postType": "",
                  "description": "",
                  "end": "",
                  "lineEnd": ""
                }
              },
              {
                "number": 7,
                "source": "*/",
                "tokens": {
                  "start": "",
                  "delimiter": "",
                  "postDelimiter": "",
                  "tag": "",
                  "postTag": "",
                  "name": "",
                  "postName": "",
                  "type": "",
                  "postType": "",
                  "description": "",
                  "end": "*/",
                  "lineEnd": ""
                }
              }
            ],
            "problems": []
          }
        ],
        "kind": "method"
      },
      {
        "type": "method",
        "id": "addItem",
        "line": 310,
        "params": [
          {
            "type": "params",
            "id": "todo",
            "line": 310
          }
        ],
        "kind": "method"
      },
      {
        "type": "method",
        "id": "addEntry",
        "line": 335,
        "params": [
          {
            "type": "params",
            "id": "entry",
            "line": 335
          }
        ],
        "kind": "method"
      },
      {
        "type": "method",
        "id": "getEntries",
        "line": 360,
        "params": [],
        "kind": "method"
      },
      {
        "type": "method",
        "id": "getItems",
        "line": 376,
        "params": [],
        "kind": "method"
      },
      {
        "type": "method",
        "id": "addEntries",
        "line": 392,
        "params": [
          {
            "type": "params",
            "id": "entries",
            "line": 392
          }
        ],
        "kind": "method"
      },
      {
        "type": "method",
        "id": "addItems",
        "line": 417,
        "params": [
          {
            "type": "params",
            "id": "items",
            "line": 417
          }
        ],
        "kind": "method"
      },
      {
        "type": "method",
        "id": "getLastEntry",
        "line": 442,
        "params": [],
        "kind": "method"
      },
      {
        "type": "method",
        "id": "getLast",
        "line": 458,
        "params": [],
        "kind": "method"
      },
      {
        "type": "method",
        "id": "getFirst",
        "line": 474,
        "params": [],
        "kind": "method"
      },
      {
        "type": "method",
        "id": "clearItem",
        "line": 490,
        "params": [
          {
            "type": "params",
            "id": "todo",
            "line": 490
          }
        ],
        "kind": "method"
      },
      {
        "type": "method",
        "id": "makeDefault",
        "line": 515,
        "params": [],
        "kind": "method"
      }
    ]
  },
  {
    "type": "class",
    "id": "FfiConverterTypeTodoList",
    "superClass": "FfiConverter",
    "line": 534,
    "methods": [
      {
        "type": "method",
        "id": "lift",
        "line": 535,
        "params": [
          {
            "type": "params",
            "id": "value",
            "line": 535
          }
        ],
        "kind": "method"
      },
      {
        "type": "method",
        "id": "lower",
        "line": 541,
        "params": [
          {
            "type": "params",
            "id": "value",
            "line": 541
          }
        ],
        "kind": "method"
      },
      {
        "type": "method",
        "id": "read",
        "line": 545,
        "params": [
          {
            "type": "params",
            "id": "dataStream",
            "line": 545
          }
        ],
        "kind": "method"
      },
      {
        "type": "method",
        "id": "write",
        "line": 549,
        "params": [
          {
            "type": "params",
            "id": "dataStream",
            "line": 549
          },
          {
            "type": "params",
            "id": "value",
            "line": 549
          }
        ],
        "kind": "method"
      },
      {
        "type": "method",
        "id": "computeSize",
        "line": 553,
        "params": [
          {
            "type": "params",
            "id": "value",
            "line": 553
          }
        ],
        "kind": "method"
      }
    ]
  },
  {
    "type": "class",
    "id": "TodoEntry",
    "line": 558,
    "methods": [
      {
        "type": "method",
        "id": "constructor",
        "line": 559,
        "params": [
          {
            "type": "params",
            "id": "text",
            "line": 559
          }
        ],
        "kind": "constructor"
      },
      {
        "type": "method",
        "id": "equals",
        "line": 570,
        "params": [
          {
            "type": "params",
            "id": "other",
            "line": 570
          }
        ],
        "kind": "method"
      }
    ]
  },
  {
    "type": "class",
    "id": "FfiConverterTypeTodoEntry",
    "superClass": "FfiConverterArrayBuffer",
    "line": 578,
    "methods": [
      {
        "type": "method",
        "id": "read",
        "line": 579,
        "params": [
          {
            "type": "params",
            "id": "dataStream",
            "line": 579
          }
        ],
        "kind": "method"
      },
      {
        "type": "method",
        "id": "write",
        "line": 584,
        "params": [
          {
            "type": "params",
            "id": "dataStream",
            "line": 584
          },
          {
            "type": "params",
            "id": "value",
            "line": 584
          }
        ],
        "kind": "method"
      },
      {
        "type": "method",
        "id": "computeSize",
        "line": 588,
        "params": [
          {
            "type": "params",
            "id": "value",
            "line": 588
          }
        ],
        "kind": "method"
      },
      {
        "type": "method",
        "id": "checkType",
        "line": 594,
        "params": [
          {
            "type": "params",
            "id": "value",
            "line": 594
          }
        ],
        "kind": "method"
      }
    ]
  },
  {
    "type": "class",
    "id": "TodoError",
    "superClass": "Error",
    "line": 610,
    "methods": []
  },
  {
    "type": "class",
    "id": "TodoDoesNotExist",
    "superClass": "TodoError",
    "line": 613,
    "methods": [
      {
        "type": "method",
        "id": "constructor",
        "line": 615,
        "params": [
          {
            "type": "params",
            "id": "message",
            "line": 615
          }
        ],
        "kind": "constructor"
      },
      {
        "type": "method",
        "id": "toString",
        "line": 619,
        "params": [],
        "kind": "method"
      }
    ]
  },
  {
    "type": "class",
    "id": "EmptyTodoList",
    "superClass": "TodoError",
    "line": 624,
    "methods": [
      {
        "type": "method",
        "id": "constructor",
        "line": 626,
        "params": [
          {
            "type": "params",
            "id": "message",
            "line": 626
          }
        ],
        "kind": "constructor"
      },
      {
        "type": "method",
        "id": "toString",
        "line": 630,
        "params": [],
        "kind": "method"
      }
    ]
  },
  {
    "type": "class",
    "id": "DuplicateTodo",
    "superClass": "TodoError",
    "line": 635,
    "methods": [
      {
        "type": "method",
        "id": "constructor",
        "line": 637,
        "params": [
          {
            "type": "params",
            "id": "message",
            "line": 637
          }
        ],
        "kind": "constructor"
      },
      {
        "type": "method",
        "id": "toString",
        "line": 641,
        "params": [],
        "kind": "method"
      }
    ]
  },
  {
    "type": "class",
    "id": "EmptyString",
    "superClass": "TodoError",
    "line": 646,
    "methods": [
      {
        "type": "method",
        "id": "constructor",
        "line": 648,
        "params": [
          {
            "type": "params",
            "id": "message",
            "line": 648
          }
        ],
        "kind": "constructor"
      },
      {
        "type": "method",
        "id": "toString",
        "line": 652,
        "params": [],
        "kind": "method"
      }
    ]
  },
  {
    "type": "class",
    "id": "DeligatedError",
    "superClass": "TodoError",
    "line": 657,
    "methods": [
      {
        "type": "method",
        "id": "constructor",
        "line": 659,
        "params": [
          {
            "type": "params",
            "id": "message",
            "line": 659
          }
        ],
        "kind": "constructor"
      },
      {
        "type": "method",
        "id": "toString",
        "line": 663,
        "params": [],
        "kind": "method"
      }
    ]
  },
  {
    "type": "class",
    "id": "FfiConverterTypeTodoError",
    "superClass": "FfiConverterArrayBuffer",
    "line": 669,
    "methods": [
      {
        "type": "method",
        "id": "read",
        "line": 670,
        "params": [
          {
            "type": "params",
            "id": "dataStream",
            "line": 670
          }
        ],
        "kind": "method"
      },
      {
        "type": "method",
        "id": "computeSize",
        "line": 686,
        "params": [
          {
            "type": "params",
            "id": "value",
            "line": 686
          }
        ],
        "kind": "method"
      },
      {
        "type": "method",
        "id": "write",
        "line": 706,
        "params": [
          {
            "type": "params",
            "id": "dataStream",
            "line": 706
          },
          {
            "type": "params",
            "id": "value",
            "line": 706
          }
        ],
        "kind": "method"
      }
    ]
  },
  {
    "type": "class",
    "id": "FfiConverterOptionalTypeTodoList",
    "superClass": "FfiConverterArrayBuffer",
    "line": 734,
    "methods": [
      {
        "type": "method",
        "id": "checkType",
        "line": 735,
        "params": [
          {
            "type": "params",
            "id": "value",
            "line": 735
          }
        ],
        "kind": "method"
      },
      {
        "type": "method",
        "id": "read",
        "line": 741,
        "params": [
          {
            "type": "params",
            "id": "dataStream",
            "line": 741
          }
        ],
        "kind": "method"
      },
      {
        "type": "method",
        "id": "write",
        "line": 753,
        "params": [
          {
            "type": "params",
            "id": "dataStream",
            "line": 753
          },
          {
            "type": "params",
            "id": "value",
            "line": 753
          }
        ],
        "kind": "method"
      },
      {
        "type": "method",
        "id": "computeSize",
        "line": 762,
        "params": [
          {
            "type": "params",
            "id": "value",
            "line": 762
          }
        ],
        "kind": "method"
      }
    ]
  },
  {
    "type": "class",
    "id": "FfiConverterSequencestring",
    "superClass": "FfiConverterArrayBuffer",
    "line": 771,
    "methods": [
      {
        "type": "method",
        "id": "read",
        "line": 772,
        "params": [
          {
            "type": "params",
            "id": "dataStream",
            "line": 772
          }
        ],
        "kind": "method"
      },
      {
        "type": "method",
        "id": "write",
        "line": 781,
        "params": [
          {
            "type": "params",
            "id": "dataStream",
            "line": 781
          },
          {
            "type": "params",
            "id": "value",
            "line": 781
          }
        ],
        "kind": "method"
      },
      {
        "type": "method",
        "id": "computeSize",
        "line": 788,
        "params": [
          {
            "type": "params",
            "id": "value",
            "line": 788
          }
        ],
        "kind": "method"
      },
      {
        "type": "method",
        "id": "checkType",
        "line": 797,
        "params": [
          {
            "type": "params",
            "id": "value",
            "line": 797
          }
        ],
        "kind": "method"
      }
    ]
  },
  {
    "type": "class",
    "id": "FfiConverterSequenceTypeTodoEntry",
    "superClass": "FfiConverterArrayBuffer",
    "line": 815,
    "methods": [
      {
        "type": "method",
        "id": "read",
        "line": 816,
        "params": [
          {
            "type": "params",
            "id": "dataStream",
            "line": 816
          }
        ],
        "kind": "method"
      },
      {
        "type": "method",
        "id": "write",
        "line": 825,
        "params": [
          {
            "type": "params",
            "id": "dataStream",
            "line": 825
          },
          {
            "type": "params",
            "id": "value",
            "line": 825
          }
        ],
        "kind": "method"
      },
      {
        "type": "method",
        "id": "computeSize",
        "line": 832,
        "params": [
          {
            "type": "params",
            "id": "value",
            "line": 832
          }
        ],
        "kind": "method"
      },
      {
        "type": "method",
        "id": "checkType",
        "line": 841,
        "params": [
          {
            "type": "params",
            "id": "value",
            "line": 841
          }
        ],
        "kind": "method"
      }
    ]
  },
  {
    "type": "function-declaration",
    "id": "getDefaultList",
    "line": 862,
    "params": []
  },
  {
    "type": "function-declaration",
    "id": "setDefaultList",
    "line": 878,
    "params": [
      "list"
    ]
  },
  {
    "type": "function-declaration",
    "id": "createEntryWith",
    "line": 903,
    "params": [
      "todo"
    ]
  }
]